beetsplug/__init__.py
beetsplug/playlistc.py
beets_playlistc-0.1.3.dist-info/LICENSE.md
beets_playlistc-0.1.3.dist-info/METADATA
beets_playlistc-0.1.3.dist-info/WHEEL
beets_playlistc-0.1.3.dist-info/top_level.txt
beets_playlistc-0.1.3.dist-info/RECORD
